[{"key":0,"request_id":"REQ2608","transaction_id":"7294-AGVB-1708409110630-t1ZB","service_name":"DevBox","date_time":"01-31-2024 22:03","service_action":"CREATE","payload":"{\"os\":\"RedHat Linux 8x\",\"cpu\":\"core\",\"memory\":\"8\",\"disk_drive\":\"500\",\"application_stack\":\"vm\"}","request_status":"completed","request_status1":"completed","created_by":"Admin","childrens":[{"key":0,"date":"01-31-2024 22:03","request_id":"REQ2608","transaction_id":"7294-AGVB-1708409110630-t1ZB","service_name":"DevBox","tool_integration":"Aria Automation","no_of_retry":0,"status":"Completed"},{"key":1,"date":"01-31-2024 22:03","request_id":"REQ2608","transaction_id":"7294-AGVB-1708409110630-t1ZB","service_name":"DevBox","tool_integration":"Puppet","no_of_retry":0,"status":"Completed"},{"key":2,"date":"01-31-2024 22:03","request_id":"REQ2608","transaction_id":"7294-AGVB-1708409110630-t1ZB","service_name":"DevBox","tool_integration":"Qualys","no_of_retry":0,"status":"Completed"},{"key":3,"date":"01-31-2024 22:03","request_id":"REQ2608","transaction_id":"7294-AGVB-1708409110630-t1ZB","service_name":"DevBox","tool_integration":"ServiceNow","no_of_retry":0,"status":"Completed"}]},{"key":1,"request_id":"REQ2706","transaction_id":"4806-OMDJ-1708409110630-k1G1","service_name":"DevBox","date_time":"01-31-2024 22:03","service_action":"CREATE","payload":"{\"os\":\"RedHat Linux 8x\",\"cpu\":\"core\",\"memory\":\"8\",\"disk_drive\":\"500\",\"application_stack\":\"vm\"}","request_status":"completed","request_status1":"completed","created_by":"Admin","childrens":[{"key":0,"date":"01-31-2024 22:03","request_id":"REQ2706","transaction_id":"4806-OMDJ-1708409110630-k1G1","service_name":"DevBox","tool_integration":"Aria Automation","no_of_retry":0,"status":"Completed"},{"key":1,"date":"01-31-2024 22:03","request_id":"REQ2706","transaction_id":"4806-OMDJ-1708409110630-k1G1","service_name":"DevBox","tool_integration":"Puppet","no_of_retry":0,"status":"Completed"},{"key":2,"date":"01-31-2024 22:03","request_id":"REQ2706","transaction_id":"4806-OMDJ-1708409110630-k1G1","service_name":"DevBox","tool_integration":"Qualys","no_of_retry":0,"status":"Completed"},{"key":3,"date":"01-31-2024 22:03","request_id":"REQ2706","transaction_id":"4806-OMDJ-1708409110630-k1G1","service_name":"DevBox","tool_integration":"ServiceNow","no_of_retry":0,"status":"Completed"}]},{"key":2,"request_id":"REQ2893","transaction_id":"6524-o6PA-1708409110630-WJjF","service_name":"DevBox","date_time":"01-31-2024 22:03","service_action":"CREATE","payload":"{\"os\":\"Windows Server 2019\",\"cpu\":\"core\",\"memory\":\"8\",\"disk_drive\":\"500\",\"application_stack\":\"vm\"}","request_status":"completed","request_status1":"completed","created_by":"Admin","childrens":[{"key":0,"date":"01-31-2024 22:03","request_id":"REQ2893","transaction_id":"6524-o6PA-1708409110630-WJjF","service_name":"DevBox","tool_integration":"Aria Automation","no_of_retry":0,"status":"Completed"},{"key":1,"date":"01-31-2024 22:03","request_id":"REQ2893","transaction_id":"6524-o6PA-1708409110630-WJjF","service_name":"DevBox","tool_integration":"Puppet","no_of_retry":0,"status":"Completed"},{"key":2,"date":"01-31-2024 22:03","request_id":"REQ2893","transaction_id":"6524-o6PA-1708409110630-WJjF","service_name":"DevBox","tool_integration":"Qualys","no_of_retry":0,"status":"Completed"},{"key":3,"date":"01-31-2024 22:03","request_id":"REQ2893","transaction_id":"6524-o6PA-1708409110630-WJjF","service_name":"DevBox","tool_integration":"ServiceNow","no_of_retry":0,"status":"Completed"}]},{"key":3,"request_id":"REQ2005","transaction_id":"2115-gLno-1708409110630-pPdc","service_name":"DevBox","date_time":"01-31-2024 22:03","service_action":"CREATE","payload":"{\"os\":\"RedHat Linux 8x\",\"cpu\":\"core\",\"memory\":\"8\",\"disk_drive\":\"500\",\"application_stack\":\"vm\"}","request_status":"completed","request_status1":"completed","created_by":"Admin","childrens":[{"key":0,"date":"01-31-2024 22:03","request_id":"REQ2005","transaction_id":"2115-gLno-1708409110630-pPdc","service_name":"DevBox","tool_integration":"Aria Automation","no_of_retry":0,"status":"Completed"},{"key":1,"date":"01-31-2024 22:03","request_id":"REQ2005","transaction_id":"2115-gLno-1708409110630-pPdc","service_name":"DevBox","tool_integration":"Puppet","no_of_retry":0,"status":"Completed"},{"key":2,"date":"01-31-2024 22:03","request_id":"REQ2005","transaction_id":"2115-gLno-1708409110630-pPdc","service_name":"DevBox","tool_integration":"Qualys","no_of_retry":0,"status":"Completed"},{"key":3,"date":"01-31-2024 22:03","request_id":"REQ2005","transaction_id":"2115-gLno-1708409110630-pPdc","service_name":"DevBox","tool_integration":"ServiceNow","no_of_retry":0,"status":"Completed"}]},{"key":4,"request_id":"REQ2259","transaction_id":"2685-CpEa-1708409110630-ZmYs","service_name":"DevBox","date_time":"01-31-2024 22:03","service_action":"CREATE","payload":"{\"os\":\"Windows Server 2019\",\"cpu\":\"core\",\"memory\":\"8\",\"disk_drive\":\"500\",\"application_stack\":\"vm\"}","request_status":"completed","request_status1":"completed","created_by":"Admin","childrens":[{"key":0,"date":"01-31-2024 22:03","request_id":"REQ2259","transaction_id":"2685-CpEa-1708409110630-ZmYs","service_name":"DevBox","tool_integration":"Aria Automation","no_of_retry":0,"status":"Completed"},{"key":1,"date":"01-31-2024 22:03","request_id":"REQ2259","transaction_id":"2685-CpEa-1708409110630-ZmYs","service_name":"DevBox","tool_integration":"Puppet","no_of_retry":0,"status":"Completed"},{"key":2,"date":"01-31-2024 22:03","request_id":"REQ2259","transaction_id":"2685-CpEa-1708409110630-ZmYs","service_name":"DevBox","tool_integration":"Qualys","no_of_retry":0,"status":"Completed"},{"key":3,"date":"01-31-2024 22:03","request_id":"REQ2259","transaction_id":"2685-CpEa-1708409110630-ZmYs","service_name":"DevBox","tool_integration":"ServiceNow","no_of_retry":0,"status":"Completed"}]},{"key":5,"request_id":"REQ2770","transaction_id":"9618-h41O-1708409110630-FeBU","service_name":"DevBox","date_time":"01-31-2024 22:03","service_action":"CREATE","payload":"{\"os\":\"Windows Server 2019\",\"cpu\":\"core\",\"memory\":\"8\",\"disk_drive\":\"500\",\"application_stack\":\"vm\"}","request_status":"completed","request_status1":"completed","created_by":"Admin","childrens":[{"key":0,"date":"01-31-2024 22:03","request_id":"REQ2770","transaction_id":"9618-h41O-1708409110630-FeBU","service_name":"DevBox","tool_integration":"Aria Automation","no_of_retry":0,"status":"Completed"},{"key":1,"date":"01-31-2024 22:03","request_id":"REQ2770","transaction_id":"9618-h41O-1708409110630-FeBU","service_name":"DevBox","tool_integration":"Puppet","no_of_retry":0,"status":"Completed"},{"key":2,"date":"01-31-2024 22:03","request_id":"REQ2770","transaction_id":"9618-h41O-1708409110630-FeBU","service_name":"DevBox","tool_integration":"Qualys","no_of_retry":0,"status":"Completed"},{"key":3,"date":"01-31-2024 22:03","request_id":"REQ2770","transaction_id":"9618-h41O-1708409110630-FeBU","service_name":"DevBox","tool_integration":"ServiceNow","no_of_retry":0,"status":"Completed"}]},{"key":6,"request_id":"REQ2403","transaction_id":"5799-Nsp9-1708409110630-0S1S","service_name":"DevBox","date_time":"01-31-2024 22:03","service_action":"CREATE","payload":"{\"os\":\"RedHat Linux 8x\",\"cpu\":\"core\",\"memory\":\"8\",\"disk_drive\":\"500\",\"application_stack\":\"vm\"}","request_status":"completed","request_status1":"completed","created_by":"Admin","childrens":[{"key":0,"date":"01-31-2024 22:03","request_id":"REQ2403","transaction_id":"5799-Nsp9-1708409110630-0S1S","service_name":"DevBox","tool_integration":"Aria Automation","no_of_retry":0,"status":"Completed"},{"key":1,"date":"01-31-2024 22:03","request_id":"REQ2403","transaction_id":"5799-Nsp9-1708409110630-0S1S","service_name":"DevBox","tool_integration":"Puppet","no_of_retry":0,"status":"Completed"},{"key":2,"date":"01-31-2024 22:03","request_id":"REQ2403","transaction_id":"5799-Nsp9-1708409110630-0S1S","service_name":"DevBox","tool_integration":"Qualys","no_of_retry":0,"status":"Completed"},{"key":3,"date":"01-31-2024 22:03","request_id":"REQ2403","transaction_id":"5799-Nsp9-1708409110630-0S1S","service_name":"DevBox","tool_integration":"ServiceNow","no_of_retry":0,"status":"Completed"}]},{"key":7,"request_id":"REQ2199","transaction_id":"4647-8PSr-1708409110630-irsa","service_name":"DevBox","date_time":"01-31-2024 22:03","service_action":"CREATE","payload":"{\"os\":\"Windows Server 2019\",\"cpu\":\"core\",\"memory\":\"8\",\"disk_drive\":\"500\",\"application_stack\":\"vm\"}","request_status":"running","request_status1":"running","created_by":"Admin","childrens":[{"key":0,"date":"01-31-2024 22:03","request_id":"REQ2199","transaction_id":"4647-8PSr-1708409110630-irsa","service_name":"DevBox","tool_integration":"Aria Automation","no_of_retry":0,"status":"Running"},{"key":1,"date":"01-31-2024 22:03","request_id":"REQ2199","transaction_id":"4647-8PSr-1708409110630-irsa","service_name":"DevBox","tool_integration":"Puppet","no_of_retry":0,"status":"Running"},{"key":2,"date":"01-31-2024 22:03","request_id":"REQ2199","transaction_id":"4647-8PSr-1708409110630-irsa","service_name":"DevBox","tool_integration":"Qualys","no_of_retry":0,"status":"Running"},{"key":3,"date":"01-31-2024 22:03","request_id":"REQ2199","transaction_id":"4647-8PSr-1708409110630-irsa","service_name":"DevBox","tool_integration":"ServiceNow","no_of_retry":0,"status":"Running"}]},{"key":8,"request_id":"REQ2807","transaction_id":"8656-DksM-1708409110630-GrWG","service_name":"DevBox","date_time":"01-31-2024 22:03","service_action":"CREATE","payload":"{\"os\":\"Windows Server 2019\",\"cpu\":\"core\",\"memory\":\"8\",\"disk_drive\":\"500\",\"application_stack\":\"vm\"}","request_status":"completed","request_status1":"completed","created_by":"Admin","childrens":[{"key":0,"date":"01-31-2024 22:03","request_id":"REQ2807","transaction_id":"8656-DksM-1708409110630-GrWG","service_name":"DevBox","tool_integration":"Aria Automation","no_of_retry":0,"status":"Completed"},{"key":1,"date":"01-31-2024 22:03","request_id":"REQ2807","transaction_id":"8656-DksM-1708409110630-GrWG","service_name":"DevBox","tool_integration":"Puppet","no_of_retry":0,"status":"Completed"},{"key":2,"date":"01-31-2024 22:03","request_id":"REQ2807","transaction_id":"8656-DksM-1708409110630-GrWG","service_name":"DevBox","tool_integration":"Qualys","no_of_retry":0,"status":"Completed"},{"key":3,"date":"01-31-2024 22:03","request_id":"REQ2807","transaction_id":"8656-DksM-1708409110630-GrWG","service_name":"DevBox","tool_integration":"ServiceNow","no_of_retry":0,"status":"Completed"}]},{"key":9,"request_id":"REQ2273","transaction_id":"9341-4FcJ-1708409110630-cM36","service_name":"DevBox","date_time":"01-31-2024 22:03","service_action":"CREATE","payload":"{\"os\":\"Windows Server 2019\",\"cpu\":\"core\",\"memory\":\"8\",\"disk_drive\":\"500\",\"application_stack\":\"vm\"}","request_status":"running","request_status1":"running","created_by":"Admin","childrens":[{"key":0,"date":"01-31-2024 22:03","request_id":"REQ2273","transaction_id":"9341-4FcJ-1708409110630-cM36","service_name":"DevBox","tool_integration":"Aria Automation","no_of_retry":1,"status":"Running"},{"key":1,"date":"01-31-2024 22:03","request_id":"REQ2273","transaction_id":"9341-4FcJ-1708409110630-cM36","service_name":"DevBox","tool_integration":"Puppet","no_of_retry":1,"status":"Running"},{"key":2,"date":"01-31-2024 22:03","request_id":"REQ2273","transaction_id":"9341-4FcJ-1708409110630-cM36","service_name":"DevBox","tool_integration":"Qualys","no_of_retry":1,"status":"Running"},{"key":3,"date":"01-31-2024 22:03","request_id":"REQ2273","transaction_id":"9341-4FcJ-1708409110630-cM36","service_name":"DevBox","tool_integration":"ServiceNow","no_of_retry":1,"status":"Running"}]},{"key":10,"request_id":"REQ2530","transaction_id":"0349-kxQ0-1708409110630-mwSn","service_name":"DevBox","date_time":"01-31-2024 22:03","service_action":"CREATE","payload":"{\"os\":\"Windows Server 2019\",\"cpu\":\"core\",\"memory\":\"8\",\"disk_drive\":\"500\",\"application_stack\":\"vm\"}","request_status":"running","request_status1":"running","created_by":"Admin","childrens":[{"key":0,"date":"01-31-2024 22:03","request_id":"REQ2530","transaction_id":"0349-kxQ0-1708409110630-mwSn","service_name":"DevBox","tool_integration":"Aria Automation","no_of_retry":0,"status":"Running"},{"key":1,"date":"01-31-2024 22:03","request_id":"REQ2530","transaction_id":"0349-kxQ0-1708409110630-mwSn","service_name":"DevBox","tool_integration":"Puppet","no_of_retry":1,"status":"Running"},{"key":2,"date":"01-31-2024 22:03","request_id":"REQ2530","transaction_id":"0349-kxQ0-1708409110630-mwSn","service_name":"DevBox","tool_integration":"Qualys","no_of_retry":0,"status":"Running"},{"key":3,"date":"01-31-2024 22:03","request_id":"REQ2530","transaction_id":"0349-kxQ0-1708409110630-mwSn","service_name":"DevBox","tool_integration":"ServiceNow","no_of_retry":0,"status":"Running"}]},{"key":11,"request_id":"REQ2802","transaction_id":"4466-wBrX-1708409110630-TJaV","service_name":"DevBox","date_time":"01-31-2024 22:03","service_action":"CREATE","payload":"{\"os\":\"Windows Server 2019\",\"cpu\":\"core\",\"memory\":\"8\",\"disk_drive\":\"500\",\"application_stack\":\"vm\"}","request_status":"completed","request_status1":"completed","created_by":"Admin","childrens":[{"key":0,"date":"01-31-2024 22:03","request_id":"REQ2802","transaction_id":"4466-wBrX-1708409110630-TJaV","service_name":"DevBox","tool_integration":"Aria Automation","no_of_retry":0,"status":"Completed"},{"key":1,"date":"01-31-2024 22:03","request_id":"REQ2802","transaction_id":"4466-wBrX-1708409110630-TJaV","service_name":"DevBox","tool_integration":"Puppet","no_of_retry":0,"status":"Completed"},{"key":2,"date":"01-31-2024 22:03","request_id":"REQ2802","transaction_id":"4466-wBrX-1708409110630-TJaV","service_name":"DevBox","tool_integration":"Qualys","no_of_retry":0,"status":"Completed"},{"key":3,"date":"01-31-2024 22:03","request_id":"REQ2802","transaction_id":"4466-wBrX-1708409110630-TJaV","service_name":"DevBox","tool_integration":"ServiceNow","no_of_retry":0,"status":"Completed"}]},{"key":12,"request_id":"REQ2119","transaction_id":"2201-czMq-1708409110630-Q1Cl","service_name":"DevBox","date_time":"01-31-2024 22:03","service_action":"CREATE","payload":"{\"os\":\"Windows Server 2019\",\"cpu\":\"core\",\"memory\":\"8\",\"disk_drive\":\"500\",\"application_stack\":\"vm\"}","request_status":"running","request_status1":"running","created_by":"Admin","childrens":[{"key":0,"date":"01-31-2024 22:03","request_id":"REQ2119","transaction_id":"2201-czMq-1708409110630-Q1Cl","service_name":"DevBox","tool_integration":"Aria Automation","no_of_retry":0,"status":"Running"},{"key":1,"date":"01-31-2024 22:03","request_id":"REQ2119","transaction_id":"2201-czMq-1708409110630-Q1Cl","service_name":"DevBox","tool_integration":"Puppet","no_of_retry":0,"status":"Running"},{"key":2,"date":"01-31-2024 22:03","request_id":"REQ2119","transaction_id":"2201-czMq-1708409110630-Q1Cl","service_name":"DevBox","tool_integration":"Qualys","no_of_retry":0,"status":"Running"},{"key":3,"date":"01-31-2024 22:03","request_id":"REQ2119","transaction_id":"2201-czMq-1708409110630-Q1Cl","service_name":"DevBox","tool_integration":"ServiceNow","no_of_retry":0,"status":"Running"}]},{"key":13,"request_id":"REQ2119","transaction_id":"1949-VWKH-1708409110630-5R8N","service_name":"DevBox","date_time":"01-31-2024 22:03","service_action":"CREATE","payload":"{\"os\":\"Windows Server 2019\",\"cpu\":\"core\",\"memory\":\"8\",\"disk_drive\":\"500\",\"application_stack\":\"vm\"}","request_status":"completed","request_status1":"completed","created_by":"Admin","childrens":[{"key":0,"date":"01-31-2024 22:03","request_id":"REQ2119","transaction_id":"1949-VWKH-1708409110630-5R8N","service_name":"DevBox","tool_integration":"Aria Automation","no_of_retry":0,"status":"Completed"},{"key":1,"date":"01-31-2024 22:03","request_id":"REQ2119","transaction_id":"1949-VWKH-1708409110630-5R8N","service_name":"DevBox","tool_integration":"Puppet","no_of_retry":0,"status":"Completed"},{"key":2,"date":"01-31-2024 22:03","request_id":"REQ2119","transaction_id":"1949-VWKH-1708409110630-5R8N","service_name":"DevBox","tool_integration":"Qualys","no_of_retry":0,"status":"Completed"},{"key":3,"date":"01-31-2024 22:03","request_id":"REQ2119","transaction_id":"1949-VWKH-1708409110630-5R8N","service_name":"DevBox","tool_integration":"ServiceNow","no_of_retry":0,"status":"Completed"}]},{"key":14,"request_id":"REQ2324","transaction_id":"7479-aKmr-1708409110630-8cRb","service_name":"DevBox","date_time":"01-31-2024 22:03","service_action":"CREATE","payload":"{\"os\":\"RedHat Linux 8x\",\"cpu\":\"core\",\"memory\":\"8\",\"disk_drive\":\"500\",\"application_stack\":\"vm\"}","request_status":"completed","request_status1":"completed","created_by":"Admin","childrens":[{"key":0,"date":"01-31-2024 22:03","request_id":"REQ2324","transaction_id":"7479-aKmr-1708409110630-8cRb","service_name":"DevBox","tool_integration":"Aria Automation","no_of_retry":0,"status":"Completed"},{"key":1,"date":"01-31-2024 22:03","request_id":"REQ2324","transaction_id":"7479-aKmr-1708409110630-8cRb","service_name":"DevBox","tool_integration":"Puppet","no_of_retry":0,"status":"Completed"},{"key":2,"date":"01-31-2024 22:03","request_id":"REQ2324","transaction_id":"7479-aKmr-1708409110630-8cRb","service_name":"DevBox","tool_integration":"Qualys","no_of_retry":0,"status":"Completed"},{"key":3,"date":"01-31-2024 22:03","request_id":"REQ2324","transaction_id":"7479-aKmr-1708409110630-8cRb","service_name":"DevBox","tool_integration":"ServiceNow","no_of_retry":0,"status":"Completed"}]}]